mockai/__init__.py
mockai/_default.py
mockai/main.py
mockai/mock_ai.py
mockai-0.0.3.dist-info/LICENSE
mockai-0.0.3.dist-info/METADATA
mockai-0.0.3.dist-info/WHEEL
mockai-0.0.3.dist-info/top_level.txt
mockai-0.0.3.dist-info/RECORD
