Metadata-Version: 2.1
Name: mockai
Version: 0.0.3
Home-page: https://github.com/chefkoch24/mockai
Author: Felix Künnecke
Author-email: kuenneckefelix@gmail.com
Classifier: Development Status :: 4 - Beta
Classifier: License :: OSI Approved :: MIT License
Classifier: Topic :: Utilities
License-File: LICENSE
Provides-Extra: dev
Requires-Dist: twine >=5.0.0 ; extra == 'dev'
Requires-Dist: pytest >=8.1.1 ; extra == 'dev'
